docproduct/__init__.py
docproduct/bert.py
docproduct/dataset.py
docproduct/get_data.py
docproduct/inference_GenerateQADoc.py
docproduct/inference_question_to_topk.py
docproduct/loss.py
docproduct/metrics.py
docproduct/models.py
docproduct/mqa_load_dataset.py
docproduct/predictor.py
docproduct/tokenization.py
docproduct/train_bertffn.py
docproduct/train_bertffn_estimator.py
docproduct/train_data_to_embedding.py
docproduct/train_embedding_to_gpt2_data.py
docproduct/train_ffn.py
docproduct/train_gpt2.py
docproduct-0.2.0.dist-info/METADATA
docproduct-0.2.0.dist-info/RECORD
docproduct-0.2.0.dist-info/WHEEL
docproduct-0.2.0.dist-info/top_level.txt
keras_bert/__init__.py
keras_bert/bert.py
keras_bert/loader.py
keras_bert/tokenizer.py
keras_bert/keras_embed_sim/__init__.py
keras_bert/keras_embed_sim/embeddings.py
keras_bert/keras_layer_normalization/__init__.py
keras_bert/keras_layer_normalization/layer_normalization.py
keras_bert/keras_multi_head/__init__.py
keras_bert/keras_multi_head/multi_head.py
keras_bert/keras_multi_head/multi_head_attention.py
keras_bert/keras_pos_embd/__init__.py
keras_bert/keras_pos_embd/pos_embd.py
keras_bert/keras_pos_embd/trig_pos_embd.py
keras_bert/keras_position_wise_feed_forward/__init__.py
keras_bert/keras_position_wise_feed_forward/feed_forward.py
keras_bert/keras_self_attention/__init__.py
keras_bert/keras_self_attention/scaled_dot_attention.py
keras_bert/keras_self_attention/seq_self_attention.py
keras_bert/keras_self_attention/seq_weighted_attention.py
keras_bert/keras_transformer/__init__.py
keras_bert/keras_transformer/gelu.py
keras_bert/keras_transformer/transformer.py
keras_bert/layers/__init__.py
keras_bert/layers/conv.py
keras_bert/layers/embedding.py
keras_bert/layers/extract.py
keras_bert/layers/inputs.py
keras_bert/layers/masked.py
keras_bert/layers/pooling.py
